{
"algo":"bst",
"titel":"Binärer Suchbaum",
"view":"tree",
"init":{"layout":"tree"},
"events":[
{"t":"note","text":"BST: kleinere Werte nach links, größere nach rechts einfügen."},
{"t":"addNode","id":0,"val":8},
{"t":"compareNode","id":0,"val":3},
{"t":"addNode","id":1,"val":3,"parent":0,"pos":"left"},
{"t":"compareNode","id":0,"val":10},
{"t":"addNode","id":2,"val":10,"parent":0,"pos":"right"},
{"t":"compareNode","id":0,"val":1},
{"t":"compareNode","id":1,"val":1},
{"t":"addNode","id":3,"val":1,"parent":1,"pos":"left"},
{"t":"compareNode","id":0,"val":6},
{"t":"compareNode","id":1,"val":6},
{"t":"addNode","id":4,"val":6,"parent":1,"pos":"right"},
{"t":"compareNode","id":0,"val":14},
{"t":"compareNode","id":2,"val":14},
{"t":"addNode","id":5,"val":14,"parent":2,"pos":"right"},
{"t":"compareNode","id":0,"val":4},
{"t":"compareNode","id":1,"val":4},
{"t":"compareNode","id":4,"val":4},
{"t":"addNode","id":6,"val":4,"parent":4,"pos":"left"},
{"t":"compareNode","id":0,"val":7},
{"t":"compareNode","id":1,"val":7},
{"t":"compareNode","id":4,"val":7},
{"t":"addNode","id":7,"val":7,"parent":4,"pos":"right"},
{"t":"compareNode","id":0,"val":13},
{"t":"compareNode","id":2,"val":13},
{"t":"compareNode","id":5,"val":13},
{"t":"addNode","id":8,"val":13,"parent":5,"pos":"left"},
{"t":"note","text":"Suche nach 7: dem Vergleichspfad von der Wurzel folgen."},
{"t":"compareNode","id":0,"val":7},
{"t":"compareNode","id":1,"val":7},
{"t":"compareNode","id":4,"val":7},
{"t":"compareNode","id":7,"val":7},
{"t":"found","i":7},
{"t":"done"}
]
}
